yc_tools/__init__.py
yc_tools/model_II.dll
yc_tools-0.1.2.dist-info/METADATA
yc_tools-0.1.2.dist-info/WHEEL
yc_tools-0.1.2.dist-info/top_level.txt
yc_tools-0.1.2.dist-info/RECORD
