Metadata-Version: 2.1
Name: yc-tools
Version: 0.1.2
Summary: yc_tools
Author: Susunl
Author-email: 1253013130@qq.com
License: MIT
Platform: any
Classifier: Programming Language :: Python :: 3
Requires-Python: >=3.5
Requires-Dist: datetime >=4.0
Requires-Dist: openpyxl >=3.0.0
Requires-Dist: pyserial >=3.5
